{"cameraMode":{"drawMode":0,"name":"Shaded","section":"Shading Mode"},"sceneLighting":true,"audioPlay":false,"sceneViewState":{"showFog":true,"showMaterialUpdate":false,"showSkybox":true,"showFlares":true,"showImageEffects":true,"showParticleSystems":true},"in2DMode":false,"pivot":{"x":-0.1983112394809723,"y":0.1689620018005371,"z":3.0751476287841799},"rotation":{"x":0.10512160509824753,"y":-0.005996056366711855,"z":0.0004348108486738056,"w":0.9945193529129028},"size":2.1368601322174074,"orthographic":false}