{"cameraMode":{"drawMode":0,"name":"Shaded","section":"Shading Mode"},"sceneLighting":true,"audioPlay":false,"sceneViewState":{"showFog":true,"showMaterialUpdate":false,"showSkybox":true,"showFlares":true,"showImageEffects":true,"showParticleSystems":true},"in2DMode":false,"pivot":{"x":-137.196533203125,"y":225.97117614746095,"z":404.1105651855469},"rotation":{"x":0.05477802827954292,"y":-0.2921905219554901,"z":0.016743315383791925,"w":0.954678475856781},"size":289.81854248046877,"orthographic":false}